webargs_starlette/__init__.py
webargs_starlette/annotations.py
webargs_starlette/py.typed
webargs_starlette/starletteparser.py
webargs_starlette-2.1.0.dist-info/LICENSE
webargs_starlette-2.1.0.dist-info/METADATA
webargs_starlette-2.1.0.dist-info/WHEEL
webargs_starlette-2.1.0.dist-info/top_level.txt
webargs_starlette-2.1.0.dist-info/RECORD
