Metadata-Version: 2.1
Name: webargs-starlette
Version: 2.1.0
Summary: Declarative request parsing and validation for Starlette with webargs
Home-page: https://github.com/sloria/webargs-starlette
Author: Steven Loria
Author-email: sloria1@gmail.com
License: MIT
Keywords: webargs,starlette,asgi,request,parsing
Classifier: Intended Audience :: Developers
Classifier: License :: OSI Approved :: MIT License
Classifier: Natural Language :: English
Classifier: Programming Language :: Python :: 3
Classifier: Programming Language :: Python :: 3.7
Classifier: Programming Language :: Python :: 3.8
Classifier: Programming Language :: Python :: 3.9
Classifier: Programming Language :: Python :: 3.10
Classifier: Programming Language :: Python :: 3.11
Classifier: Topic :: Internet :: WWW/HTTP
License-File: LICENSE
Requires-Dist: webargs (~=8.0)
Requires-Dist: starlette (>=0.21.0)
Requires-Dist: marshmallow (~=3.0)
Provides-Extra: dev
Requires-Dist: pytest ; extra == 'dev'
Requires-Dist: mock ; extra == 'dev'
Requires-Dist: webtest (~=2.0.32) ; extra == 'dev'
Requires-Dist: webtest-asgi (~=1.1.0) ; extra == 'dev'
Requires-Dist: mypy (==0.971) ; extra == 'dev'
Requires-Dist: flake8 (==5.0.4) ; extra == 'dev'
Requires-Dist: flake8-bugbear (==22.8.23) ; extra == 'dev'
Requires-Dist: pre-commit (~=2.20) ; extra == 'dev'
Requires-Dist: httpie ; extra == 'dev'
Requires-Dist: uvicorn ; extra == 'dev'
Requires-Dist: tox ; extra == 'dev'
Provides-Extra: examples
Requires-Dist: httpie ; extra == 'examples'
Requires-Dist: uvicorn ; extra == 'examples'
Provides-Extra: lint
Requires-Dist: mypy (==0.971) ; extra == 'lint'
Requires-Dist: flake8 (==5.0.4) ; extra == 'lint'
Requires-Dist: flake8-bugbear (==22.8.23) ; extra == 'lint'
Requires-Dist: pre-commit (~=2.20) ; extra == 'lint'
Provides-Extra: tests
Requires-Dist: pytest ; extra == 'tests'
Requires-Dist: mock ; extra == 'tests'
Requires-Dist: webtest (~=2.0.32) ; extra == 'tests'
Requires-Dist: webtest-asgi (~=1.1.0) ; extra == 'tests'
